templang/__init__.py
templang/main.py
templang-0.1.1.dist-info/METADATA
templang-0.1.1.dist-info/WHEEL
templang-0.1.1.dist-info/top_level.txt
templang-0.1.1.dist-info/RECORD
