Metadata-Version: 2.1
Name: templang
Version: 0.1.1
Summary: A simple annotation-based language to generate code from templates
Author-email: Marcel Claramunt <marcel@moveread.com>
Project-URL: repo, https://github.com/marciclabas/codegen.git
Requires-Python: >=3.10
Requires-Dist: haskellian
